splitnewton/__init__.py
splitnewton/newton.py
splitnewton/split_newton.py
SplitNewton-0.3.1.dist-info/LICENSE.md
SplitNewton-0.3.1.dist-info/METADATA
SplitNewton-0.3.1.dist-info/WHEEL
SplitNewton-0.3.1.dist-info/top_level.txt
SplitNewton-0.3.1.dist-info/RECORD
