Metadata-Version: 2.1
Name: SplitNewton
Version: 0.3.1
Summary: Split Newton Solver
Home-page: https://github.com/gpavanb1/SplitNewton
Author: gpavanb1
Author-email: gpavanb@gmail.com
License: MIT
Project-URL: Bug Reports, https://github.com/gpavanb1/SplitNewton/issues
Project-URL: Source, https://github.com/gpavanb1/SplitNewton/
Keywords: newton python continuation armijo optimization pseudotransient splitting
Platform: UNKNOWN
Classifier: Topic :: Scientific/Engineering :: Mathematics
Classifier: License :: OSI Approved :: MIT License
Classifier: Programming Language :: Python :: 3
Classifier: Programming Language :: Python :: 3 :: Only
Requires-Dist: numpy
Requires-Dist: scipy
